mcqa_utils/__init__.py
mcqa_utils/answer.py
mcqa_utils/dataset.py
mcqa_utils/evaluate.py
mcqa_utils/mcqa_utils.py
mcqa_utils/metric.py
mcqa_utils/question_answering.py
mcqa_utils/threshold.py
mcqa_utils/utils.py
mcqa_utils-0.7.0.dist-info/AUTHORS.rst
mcqa_utils-0.7.0.dist-info/LICENSE
mcqa_utils-0.7.0.dist-info/METADATA
mcqa_utils-0.7.0.dist-info/WHEEL
mcqa_utils-0.7.0.dist-info/entry_points.txt
mcqa_utils-0.7.0.dist-info/top_level.txt
mcqa_utils-0.7.0.dist-info/RECORD
