Metadata-Version: 2.1
Name: mcqa-utils
Version: 0.7.0
Summary: Multiple Choice Evaluation utilities
Home-page: https://github.com/geblanco/mcqa_utils
Author: Guillermo E. Blanco
Author-email: geblanco@lsi.uned.es
License: MIT license
Keywords: mcqa_utils
Platform: UNKNOWN
Classifier: Development Status :: 2 - Pre-Alpha
Classifier: Intended Audience :: Developers
Classifier: License :: OSI Approved :: MIT License
Classifier: Natural Language :: English
Classifier: Programming Language :: Python :: 3
Classifier: Programming Language :: Python :: 3.8
Requires-Python: >=3.5
License-File: LICENSE
License-File: AUTHORS.rst
Requires-Dist: mc-transformers (==0.2.0)
Requires-Dist: numpy (==1.19.3)
Requires-Dist: scikit-learn (==1.0)
